bor/bor.py
bor/color.py
bor-0.2.0.dist-info/LICENSE
bor-0.2.0.dist-info/METADATA
bor-0.2.0.dist-info/WHEEL
bor-0.2.0.dist-info/entry_points.txt
bor-0.2.0.dist-info/top_level.txt
bor-0.2.0.dist-info/RECORD
